randiter/__init__.py
randiter/randiter.py
randiter-0.1.0.dist-info/LICENSE
randiter-0.1.0.dist-info/WHEEL
randiter-0.1.0.dist-info/METADATA
randiter-0.1.0.dist-info/RECORD
