Metadata-Version: 2.1
Name: randiter
Version: 0.1.0
Summary: Randomly iterate a sequence with buffered shuffling
Home-page: https://github.com/hkiyomaru/randiter
License: MIT
Author: Hirokazu Kiyomaru
Author-email: h.kiyomaru@gmail.com
Requires-Python: >=3.8,<4.0
Classifier: License :: OSI Approved :: MIT License
Classifier: Programming Language :: Python :: 3
Classifier: Programming Language :: Python :: 3.8
Classifier: Programming Language :: Python :: 3.9
Project-URL: Repository, https://github.com/hkiyomaru/randiter
